canada_holiday/__init__.py
canada_holiday/holiday.py
canada_holiday/holiday_info/__init__.py
canada_holiday/holiday_info/ab.py
canada_holiday/holiday_info/all.py
canada_holiday/holiday_info/bc.py
canada_holiday/holiday_info/mb.py
canada_holiday/holiday_info/national.py
canada_holiday/holiday_info/nb.py
canada_holiday/holiday_info/nl.py
canada_holiday/holiday_info/ns.py
canada_holiday/holiday_info/nt.py
canada_holiday/holiday_info/nu.py
canada_holiday/holiday_info/on.py
canada_holiday/holiday_info/pe.py
canada_holiday/holiday_info/qc.py
canada_holiday/holiday_info/sk.py
canada_holiday/holiday_info/yt.py
canada_holiday/holidays.py
canada_holiday/utils.py
canada_holiday-1.2.0.dist-info/LICENSE
canada_holiday-1.2.0.dist-info/METADATA
canada_holiday-1.2.0.dist-info/WHEEL
canada_holiday-1.2.0.dist-info/RECORD
