Metadata-Version: 2.1
Name: canada-holiday
Version: 1.2.0
Summary: Python package for Canadian holidays
Home-page: https://github.com/kmsunmin/canada-holiday
Author: Sunmin Kim
Author-email: kmsunmin@gmail.com
Requires-Python: >=3.12,<4.0
Classifier: Programming Language :: Python :: 3
Project-URL: Repository, https://github.com/kmsunmin/canada-holiday
